{"data":{"site":{"siteMetadata":{"siteUrl":"https://wwfalcon.github.io/sdc_toolkits_page/","title":"PSD SDC Toolkits","description":"PSD SDC Toolkits."}},"markdownRemark":{"frontmatter":{"title":"营销应用","date":null,"date_pretty":null,"path":null,"meta_title":null,"meta_description":null,"image":null,"next":null,"sidebar":null,"toc":null,"keywords":null},"html":"<h3 id=\"营销应用\"><a href=\"#%E8%90%A5%E9%94%80%E5%BA%94%E7%94%A8\" aria-hidden class=\"anchor\"><svg aria-hidden=\"true\" height=\"16\" version=\"1.1\" viewBox=\"0 0 16 16\" width=\"16\"><path fill-rule=\"evenodd\" d=\"M4 9h1v1H4c-1.5 0-3-1.69-3-3.5S2.55 3 4 3h4c1.45 0 3 1.69 3 3.5 0 1.41-.91 2.72-2 3.25V8.59c.58-.45 1-1.27 1-2.09C10 5.22 8.98 4 8 4H4c-.98 0-2 1.22-2 2.5S3 9 4 9zm9-3h-1v1h1c1 0 2 1.22 2 2.5S13.98 12 13 12H9c-.98 0-2-1.22-2-2.5 0-.83.42-1.64 1-2.09V6.25c-1.09.53-2 1.84-2 3.25C6 11.31 7.55 13 9 13h4c1.45 0 3-1.69 3-3.5S14.5 6 13 6z\"></path></svg></a>营销应用</h3>\n<p>营销辩论：全国品牌的生产商处否也该提供自有品牌的产品？</p>\n<p>一些大品牌公司提供（零售商）自有品牌产品是有争议的举措。例如，罗森普瑞纳（Ralstorv\nPurina），Borden，康纳格拉（Con\nAgra）以及亨氏（Heinz）都计划提供一些质虽稍差的产品作为自有品牌产品。其他生产商指责这种\"打不过就加入\"的策略保护了这些自有品牌产品，导致混乱，甚至在消费者脑子里强化了一种概念：所有同类产品都是一样的。</p>\n<p>辩论双方</p>\n<p>正方观点：生产商有权利选择销售自有品牌产品以便增加收入。</p>\n<p>反方观点：他们压根就不应该涉及自有品牌产品。</p>\n<p>营销讨论</p>\n<p>回忆一下你最喜欢的商店。他们做了什么让你忠实于他们？在你很多次店内体验中你最喜欢哪一次？他们还可以做哪些改进？</p>","fields":{"slug":"/ebooks/marketing_mgt/ch139/"},"timeToRead":1,"excerpt":"营销应用 营销辩论：全国品牌的生产商处否也该提供自有品牌的产品？ 一些大品牌公司提供（零售商）自有品牌产品是有争议的举措。例如，罗森普瑞纳（Ralstorv\nPurina），Borden，康纳格拉（Con\nAgra）以及亨氏（Heinz…","fileAbsolutePath":"/Users/gavinwang/Documents/Working/codes/sdc_toolkits/content/ebooks/marketing_mgt/ch139.md"}},"pageContext":{"slug":"/ebooks/marketing_mgt/ch139/"}}